LunarCalendar-0.0.8.dist-info/METADATA
LunarCalendar-0.0.8.dist-info/RECORD
LunarCalendar-0.0.8.dist-info/WHEEL
LunarCalendar-0.0.8.dist-info/entry_points.txt
LunarCalendar-0.0.8.dist-info/top_level.txt
lunarcalendar/__init__.py
lunarcalendar/_calc.py
lunarcalendar/_compact.py
lunarcalendar/basefestival.py
lunarcalendar/color.py
lunarcalendar/command.py
lunarcalendar/converter.py
lunarcalendar/festival.py
lunarcalendar/solarterm.py
