Metadata-Version: 2.1
Name: LunarCalendar
Version: 0.0.8
Summary: A lunar calendar converter, including a number of lunar and solar holidays, mainly from China.
Home-page: https://github.com/wolfhong/LunarCalendar
Author: wolfhong
Author-email: hongxucai1991@gmail.com
License: MIT
Keywords: lunar calendar,festival,Chinese festivals,24 solar terms,solar calendar,lunar solar converter,lunisolar calendar
Platform: UNKNOWN
Classifier: License :: OSI Approved :: MIT License
Classifier: Programming Language :: Python
Classifier: Programming Language :: Python :: 2
Classifier: Programming Language :: Python :: 3
Classifier: Development Status :: 4 - Beta
Classifier: Intended Audience :: Developers
Classifier: Topic :: Software Development :: Libraries
Classifier: Topic :: Utilities
Requires-Python: >=2.7, <4
Requires-Dist: python-dateutil (>=2.6.1)
Requires-Dist: ephem (>=3.7.5.3)
Requires-Dist: pytz
